jd_image_processing/__init__.py
jd_image_processing/processing/__init__.py
jd_image_processing/processing/combination.py
jd_image_processing/processing/transformation.py
jd_image_processing/utils/__init__.py
jd_image_processing/utils/io.py
jd_image_processing/utils/plot.py
jd_image_processing-0.0.1.dist-info/METADATA
jd_image_processing-0.0.1.dist-info/WHEEL
jd_image_processing-0.0.1.dist-info/top_level.txt
jd_image_processing-0.0.1.dist-info/RECORD
