Metadata-Version: 2.1
Name: jd-image-processing
Version: 0.0.1
Summary: Image Processing
Home-page: https://github.com/Judenilson/dio-python-bootcamp/tree/main/package-project
Author: judenilson
Author-email: judenilson@hotmail.com
Requires-Python: >=3.8
Requires-Dist: scikit-image
Requires-Dist: matplotlib
